pygh2md/GitHubAdapter.py
pygh2md/PyGh2Md.py
pygh2md/__init__.py
pygh2md/_version.py
pygh2md/exceptions/InvalidDateFormatException.py
pygh2md/exceptions/NoGitHubAccessTokenException.py
pygh2md/exceptions/UnknownGitHubRepositoryException.py
pygh2md/exceptions/__init__.py
pygh2md/resources/__init__.py
pygh2md/resources/loggingConfiguration.json
pygh2md-0.2.0.dist-info/LICENSE
pygh2md-0.2.0.dist-info/METADATA
pygh2md-0.2.0.dist-info/WHEEL
pygh2md-0.2.0.dist-info/entry_points.txt
pygh2md-0.2.0.dist-info/top_level.txt
pygh2md-0.2.0.dist-info/RECORD
